syn_ram.v
// Design Program for 16X2 Synchronous RAM

module syn_ram (clk, rst, we, oe, addr, din, dout);
    input wire clk;            // system clock
    input wire rst;            // reset for output register
    input wire we;             // write enable: for 1 - write, for 0 - read
    input wire oe;             // output enable: for 1 - drive dout, for 0 - disable output
    input wire [3:0] addr;     // 4-bits address 
    input wire [1:0] din;      // 2-bits data i/p
    output wire [1:0] dout;    // 2-bits data o/p

    reg [1:0] mem [0:15];      // 16 loc, each 2 bits wide
    reg [1:0] dout_reg;        // registered read o/p

    always @(posedge clk) begin

        if (rst) begin
            dout_reg <= 2'b00;  // rst = high, clear o/p reg
        end 
        else begin
            dout_reg <= mem[addr];    // syn read
        end

        if (we) begin
            mem[addr] <= din; // syn write at clk edge if we = high
        end
    end

assign dout = oe ? dout_reg : 2'b00;  // o/p enable
    
endmodule

syn_ram_tb.v
// Testbench for the 16X2 Synchronous RAM Module

`timescale 1ns/1ps 
`include "syn_ram.v"

module syn_ram_tb;

reg clk;
reg rst;
reg oe;
reg we;
reg [3:0] addr;
reg [1:0] din;
wire [1:0] dout;

// instantiate RAM module
syn_ram dut(.clk(clk), .rst(rst), .we(we), .oe(oe), .addr(addr), .din(din), .dout(dout));

// clk generation
always #5 clk = ~ clk;

initial begin

    $dumpfile("syn_ram_tb.vcd"); //create a cvd file
    $dumpvars(0, syn_ram_tb);

    clk = 0;       // Initializing 
    rst = 1;
    oe = 1;
    we = 0;
    addr = 0;
    din = 0;

    #12 rst = 0;   // Release reset

    we = 1;        // Write operation
    addr = 4'd3;
    din = 2'b10;
    #10;           // delay

    addr = 4'd7;
    din = 2'b01;
    #10;

    we = 0;          // Read operation
    addr = 4'd3;
    #10; 

    addr = 4'd7;
    #10;

    $stop;

end

endmodule

syn_ram_tb.vcd
$date
	Fri Nov 21 21:32:37 2025
$end
$version
	Icarus Verilog
$end
$timescale
	1ps
$end
$scope module syn_ram_tb $end
$var wire 2 ! dout [1:0] $end
$var reg 4 " addr [3:0] $end
$var reg 1 # clk $end
$var reg 2 $ din [1:0] $end
$var reg 1 % oe $end
$var reg 1 & rst $end
$var reg 1 ' we $end
$scope module dut $end
$var wire 4 ( addr [3:0] $end
$var wire 1 # clk $end
$var wire 2 ) din [1:0] $end
$var wire 1 % oe $end
$var wire 1 & rst $end
$var wire 1 ' we $end
$var wire 2 * dout [1:0] $end
$var reg 2 + dout_reg [1:0] $end
$upscope $end
$upscope $end
$enddefinitions $end
$comment Show the parameter values. $end
$dumpall
$end
#0
$dumpvars
bx +
bx *
b0 )
b0 (
0'
1&
1%
b0 $
0#
b0 "
bx !
$end
#5000
b0 !
b0 *
b0 +
1#
#10000
0#
#12000
b10 $
b10 )
b11 "
b11 (
1'
0&
#15000
bx !
bx *
bx +
1#
#20000
0#
#22000
b1 $
b1 )
b111 "
b111 (
#25000
1#
#30000
0#
#32000
b11 "
b11 (
0'
#35000
b10 !
b10 *
b10 +
1#
#40000
0#
#42000
b111 "
b111 (
#45000
b1 !
b1 *
b1 +
1#
